periskop_client/__init__.py
periskop_client/collector.py
periskop_client/exporter.py
periskop_client/handler.py
periskop_client/models.py
periskop_client-0.2.0.dist-info/LICENSE
periskop_client-0.2.0.dist-info/WHEEL
periskop_client-0.2.0.dist-info/METADATA
periskop_client-0.2.0.dist-info/RECORD
