Metadata-Version: 2.1
Name: periskop-client
Version: 0.2.0
Summary: Periskop Python client
License: Apache-2.0
Author: Marc Tuduri
Author-email: marc.tuduri@soundcloud.com
Requires-Python: >=3.6,<4.0
Classifier: Intended Audience :: Developers
Classifier: License :: OSI Approved :: Apache Software License
Classifier: Operating System :: OS Independent
Classifier: Programming Language :: Python
Classifier: Programming Language :: Python :: 3
Classifier: Programming Language :: Python :: 3.6
Classifier: Programming Language :: Python :: 3.7
Classifier: Programming Language :: Python :: 3.8
Classifier: Topic :: Software Development
Requires-Dist: dataclasses-json (>=0.4.2,<0.5.0)
